{
    "0": [
        "Bba",
        "English",
        "Second Language",
        "English",
        "Bba"
    ],
    "1": [
        "Second Language",
        "English",
        "Bba",
        "Bba",
        "English"
    ],
    "2": [
        "English",
        "Bba",
        "Bba",
        "English",
        "Second Language"
    ],
    "3": [
        "English",
        "Bba",
        "English",
        "Second Language",
        "Bba"
    ],
    "4": [
        "Second Language",
        "Bba",
        "Bba",
        "Bba",
        "English"
    ]
}