{
    "0": [
        "Software Engineering",
        "OOP Python",
        "Physics",
        "Mathematics",
        "RDBMS"
    ],
    "1": [
        "OOP Python",
        "Mathematics",
        "Physics",
        "Physics Lab",
        "Physics Lab"
    ],
    "2": [
        "RDBMS",
        "Software Engineering",
        "OOP Python",
        "RDBMS Lab",
        "RDBMS Lab"
    ],
    "3": [
        "Mathematics",
        "OOP Python",
        "RDBMS Lab",
        "Software Engineering",
        "RDBMS"
    ],
    "4": [
        "Physics",
        "Mathematics",
        "Mathematics",
        "Software Engineering",
        "RDBMS Lab"
    ]
}
